zowe/core_for_zowe_sdk/__init__.py
zowe/core_for_zowe_sdk/connection.py
zowe/core_for_zowe_sdk/constants.py
zowe/core_for_zowe_sdk/exceptions.py
zowe/core_for_zowe_sdk/request_handler.py
zowe/core_for_zowe_sdk/sdk_api.py
zowe/core_for_zowe_sdk/zosmf_profile.py
zowe_core_for_zowe_sdk-0.5.0.dist-info/METADATA
zowe_core_for_zowe_sdk-0.5.0.dist-info/WHEEL
zowe_core_for_zowe_sdk-0.5.0.dist-info/top_level.txt
zowe_core_for_zowe_sdk-0.5.0.dist-info/RECORD
